snowprofile/__init__.py
snowprofile/_base_classes.py
snowprofile/_constants.py
snowprofile/_utils.py
snowprofile/classes.py
snowprofile/profiles.py
snowprofile/snowprofile.py
snowprofile/stability_tests.py
snowprofile/io/__init__.py
snowprofile/io/_caaml6_xml_read.py
snowprofile/io/_caaml6_xml_write.py
snowprofile/io/_caaml_parse_utils.py
snowprofile/io/caaml6_json.py
snowprofile/io/caaml6_xml.py
snowprofile/io/internal_json.py
snowprofile/io/mf_bdclim.py
snowprofile/io/profile_csv.py
snowprofile/plot/SnowSymbolsIACS.ttf
snowprofile/plot/__init__.py
snowprofile/plot/plot_dictionnaries.py
snowprofile/plot/plot_full.py
snowprofile/plot/plot_simple.py
snowprofile/plot/plot_utils.py
snowprofile-0.1.2.dist-info/licenses/LICENCE-en.txt
snowprofile-0.1.2.dist-info/licenses/LICENCE.txt
snowprofile-0.1.2.dist-info/METADATA
snowprofile-0.1.2.dist-info/WHEEL
snowprofile-0.1.2.dist-info/top_level.txt
snowprofile-0.1.2.dist-info/RECORD
