Metadata-Version: 2.4
Name: snowprofile
Version: 0.1.2
Summary: Tools to read, write and process punctual snow profiles. It includes tools to read and write from and to the international CAAML format.
License: 
Project-URL: Homepage, https://github.com/UMR-CNRM/snowprofile
Project-URL: Repository, https://github.com/UMR-CNRM/snowprofile
Keywords: snow profile,CAAML
Classifier: Development Status :: 4 - Beta
Classifier: License :: CeCILL-C Free Software License Agreement (CECILL-C)
Requires-Python: >=3.8
License-File: LICENCE-en.txt
License-File: LICENCE.txt
Requires-Dist: pydantic<3,>=2
Requires-Dist: pandas
Requires-Dist: numpy
Provides-Extra: doc
Requires-Dist: sphinx; extra == "doc"
Requires-Dist: autodoc_pydantic; extra == "doc"
Provides-Extra: tests
Requires-Dist: pytest; extra == "tests"
Requires-Dist: lxml; extra == "tests"
Provides-Extra: plots
Requires-Dist: matplotlib; extra == "plots"
Dynamic: license-file
